autopylog/__init__.py
autopylog/core.py
tests/test_sample.py
wheel_chec/autopylog/__init__.py
wheel_chec/autopylog/core.py
autopylog-0.1.0.dist-info/METADATA
autopylog-0.1.0.dist-info/WHEEL
autopylog-0.1.0.dist-info/top_level.txt
autopylog-0.1.0.dist-info/RECORD
