Metadata-Version: 2.4
Name: autopylog
Version: 0.1.0
Summary: Automatically log function input, output, execution time, and exceptions.
Author-email: "A. Aravind Raj" <araj7322@gmail.com>
License: MIT
Classifier: Programming Language :: Python :: 3
Classifier: License :: OSI Approved :: MIT License
Classifier: Operating System :: OS Independent
Requires-Python: >=3.6
